pyfr42/__init__.py
pyfr42/pyfr42.py
pyfr42-2.1.0.dist-info/METADATA
pyfr42-2.1.0.dist-info/WHEEL
pyfr42-2.1.0.dist-info/top_level.txt
pyfr42-2.1.0.dist-info/RECORD
