Metadata-Version: 2.1
Name: pyfr42
Version: 2.1.0
Summary: zxczxczxc
Author: asd dasd
Requires-Python: >=3.6
Requires-Dist: pyperclip
Requires-Dist: openai
